README.md
async_case.py
setup.cfg
setup.py
async_case.egg-info/PKG-INFO
async_case.egg-info/SOURCES.txt
async_case.egg-info/dependency_links.txt
async_case.egg-info/top_level.txt