Metadata-Version: 2.1
Name: async-case
Version: 3.8.1
Summary: Backport of Python 3.8's unittest.async_case
Home-page: https://github.com/nvllsvm/async_case
Author: Andrew Rabert
Author-email: ar@nullsum.net
License: UNKNOWN
Platform: UNKNOWN
